pyiskra/__init__.py
pyiskra/discovery.py
pyiskra/exceptions.py
pyiskra/helper.py
pyiskra-1.0.2.dist-info/METADATA
pyiskra-1.0.2.dist-info/WHEEL
pyiskra-1.0.2.dist-info/top_level.txt
pyiskra-1.0.2.dist-info/RECORD
