Metadata-Version: 2.1
Name: pyiskra
Version: 1.0.2
Summary: Python Iskra devices interface
Home-page: https://github.com/Iskramis/pyiskra
Author: Iskra d.o.o.
Author-email: razvoj.mis@iskra.eu
Maintainer: Iskra <razvoj.mis@iskra.eu>
License: GPL
Keywords: homeautomation,iskra,energy meter
Classifier: Programming Language :: Python :: 3
Classifier: License :: OSI Approved :: GNU General Public License v3 (GPLv3)
Classifier: Operating System :: OS Independent
Classifier: Topic :: Software Development :: Libraries :: Application Frameworks
Classifier: Topic :: Home Automation
Requires-Python: >=3.8
Requires-Dist: netifaces
Requires-Dist: aiohttp
Requires-Dist: pymodbus
